[
  {
    "data": "2026-07-11T22:01:23.841Z",
    "resultado": "aguardando_intervalo",
    "mensagem": "Aguardando intervalo de 2h entre posts. Faltam 32 min."
  },
  {
    "data": "2026-07-11T21:53:04.168Z",
    "resultado": "aguardando_intervalo",
    "mensagem": "Aguardando intervalo de 2h entre posts. Faltam 41 min."
  },
  {
    "data": "2026-07-11T21:31:21.237Z",
    "resultado": "aguardando_intervalo",
    "mensagem": "Aguardando intervalo de 2h entre posts. Faltam 62 min."
  },
  {
    "data": "2026-07-11T21:01:32.643Z",
    "resultado": "aguardando_intervalo",
    "mensagem": "Aguardando intervalo de 2h entre posts. Faltam 92 min."
  },
  {
    "data": "2026-07-11T20:53:14.736Z",
    "resultado": "aguardando_intervalo",
    "mensagem": "Aguardando intervalo de 2h entre posts. Faltam 101 min."
  },
  {
    "data": "2026-07-11T20:33:16.581Z",
    "resultado": "postado",
    "mensagem": "Postagem realizada com sucesso (carrossel): \"Federação alemã diz estar confiante sobre contratação de técnico Klopp para a seleção\".",
    "postId": "17993262977809125",
    "storyId": "18134541682592740",
    "reelId": null,
    "tipo": "carrossel"
  },
  {
    "data": "2026-07-11T20:31:46.687Z",
    "resultado": "noticia_encontrada",
    "mensagem": "Notícia nova encontrada (peso 21): \"Federação alemã diz estar confiante sobre contratação de técnico Klopp para a seleção\". Realizando postagem..."
  },
  {
    "data": "2026-07-11T20:01:23.333Z",
    "resultado": "aguardando_intervalo",
    "mensagem": "Aguardando intervalo de 2h entre posts. Faltam 1 min."
  },
  {
    "data": "2026-07-11T19:45:05.780Z",
    "resultado": "aguardando_intervalo",
    "mensagem": "Aguardando intervalo de 2h entre posts. Faltam 18 min."
  },
  {
    "data": "2026-07-11T19:31:24.219Z",
    "resultado": "aguardando_intervalo",
    "mensagem": "Aguardando intervalo de 2h entre posts. Faltam 31 min."
  },
  {
    "data": "2026-07-11T19:01:17.797Z",
    "resultado": "aguardando_intervalo",
    "mensagem": "Aguardando intervalo de 2h entre posts. Faltam 62 min."
  },
  {
    "data": "2026-07-11T18:31:42.119Z",
    "resultado": "aguardando_intervalo",
    "mensagem": "Aguardando intervalo de 2h entre posts. Faltam 91 min."
  },
  {
    "data": "2026-07-11T18:27:43.583Z",
    "resultado": "aguardando_intervalo",
    "mensagem": "Aguardando intervalo de 2h entre posts. Faltam 95 min."
  },
  {
    "data": "2026-07-11T18:02:22.660Z",
    "resultado": "postado",
    "mensagem": "Postagem realizada com sucesso (card): \"Demanda ampla por IA é o fator-chave para investidores da Nvidia, diz Morgan Stanley\".",
    "postId": "17901907611464568",
    "storyId": "18602479855049363",
    "reelId": null,
    "tipo": "card"
  },
  {
    "data": "2026-07-11T18:01:32.322Z",
    "resultado": "noticia_encontrada",
    "mensagem": "Notícia nova encontrada (peso 13): \"Demanda ampla por IA é o fator-chave para investidores da Nvidia, diz Morgan Stanley\". Realizando postagem..."
  },
  {
    "data": "2026-07-11T17:31:20.929Z",
    "resultado": "aguardando_intervalo",
    "mensagem": "Aguardando intervalo de 2h entre posts. Faltam 2 min."
  },
  {
    "data": "2026-07-11T17:02:18.045Z",
    "resultado": "aguardando_intervalo",
    "mensagem": "Aguardando intervalo de 2h entre posts. Faltam 31 min."
  },
  {
    "data": "2026-07-11T17:01:29.245Z",
    "resultado": "aguardando_intervalo",
    "mensagem": "Aguardando intervalo de 2h entre posts. Faltam 32 min."
  },
  {
    "data": "2026-07-11T16:31:14.461Z",
    "resultado": "aguardando_intervalo",
    "mensagem": "Aguardando intervalo de 2h entre posts. Faltam 62 min."
  },
  {
    "data": "2026-07-11T16:01:26.570Z",
    "resultado": "aguardando_intervalo",
    "mensagem": "Aguardando intervalo de 2h entre posts. Faltam 92 min."
  },
  {
    "data": "2026-07-11T15:33:41.182Z",
    "resultado": "aguardando_intervalo",
    "mensagem": "Aguardando intervalo de 2h entre posts. Faltam 120 min."
  },
  {
    "data": "2026-07-11T15:32:52.296Z",
    "resultado": "postado",
    "mensagem": "Postagem realizada com sucesso (carrossel): \"Bitcoin (BTC) sobe e mantém nível dos US$ 64 mil com otimismo do setor de tecnologia; veja preços das criptomoedas neste sábado (11)\".",
    "postId": "18038388149803065",
    "storyId": "17898022701509861",
    "reelId": null,
    "tipo": "carrossel"
  },
  {
    "data": "2026-07-11T15:31:15.776Z",
    "resultado": "noticia_encontrada",
    "mensagem": "Notícia nova encontrada (peso 45): \"Bitcoin (BTC) sobe e mantém nível dos US$ 64 mil com otimismo do setor de tecnologia; veja preços das criptomoedas neste sábado (11)\". Realizando postagem..."
  },
  {
    "data": "2026-07-11T15:02:44.954Z",
    "resultado": "reel_postado",
    "mensagem": "Resumo em vídeo do dia publicado com 2 notícia(s).",
    "reelId": "18217695667328011",
    "videoUrl": "https://raw.githubusercontent.com/convexanews/convexanews.github.io/main/bdi-cards/resumo-1783782102067.mp4",
    "noticias": [
      "HSAF11 mantém dividendos em R$ 0,95 por cota pelo 18º mês",
      "XP mantém otimismo com PIB e prevê dólar a R$ 5,00; veja os destaques da semana"
    ]
  },
  {
    "data": "2026-07-11T15:01:29.746Z",
    "resultado": "aguardando_intervalo",
    "mensagem": "Aguardando intervalo de 2h entre posts. Faltam 2 min."
  },
  {
    "data": "2026-07-11T14:31:36.019Z",
    "resultado": "aguardando_intervalo",
    "mensagem": "Aguardando intervalo de 2h entre posts. Faltam 32 min."
  },
  {
    "data": "2026-07-11T14:25:28.273Z",
    "resultado": "comparativo_precos",
    "mensagem": "Comparativo de preços publicado. Ibovespa +30,1%, Dólar -8,5%, Bitcoin -45,3%.",
    "postId": "18086185454434638"
  },
  {
    "data": "2026-07-11T14:04:20.062Z",
    "resultado": "aguardando_intervalo",
    "mensagem": "Aguardando intervalo de 2h entre posts. Faltam 59 min."
  },
  {
    "data": "2026-07-11T14:01:20.384Z",
    "resultado": "aguardando_intervalo",
    "mensagem": "Aguardando intervalo de 2h entre posts. Faltam 62 min."
  },
  {
    "data": "2026-07-11T13:31:19.907Z",
    "resultado": "aguardando_intervalo",
    "mensagem": "Aguardando intervalo de 2h entre posts. Faltam 92 min."
  },
  {
    "data": "2026-07-11T13:03:15.509Z",
    "resultado": "postado",
    "mensagem": "Postagem realizada com sucesso (reel): \"Haddad, sobre taxa de juros: Banco Central está criando problema desnecessariamente\".",
    "postId": "18418887697181121",
    "storyId": null,
    "reelId": "18418887697181121",
    "tipo": "reel"
  },
  {
    "data": "2026-07-11T13:01:24.041Z",
    "resultado": "noticia_encontrada",
    "mensagem": "Notícia nova encontrada (peso 49): \"Haddad, sobre taxa de juros: Banco Central está criando problema desnecessariamente\". Realizando postagem..."
  },
  {
    "data": "2026-07-11T12:31:27.182Z",
    "resultado": "aguardando_intervalo",
    "mensagem": "Aguardando intervalo de 2h entre posts. Faltam 1 min."
  },
  {
    "data": "2026-07-11T12:30:04.807Z",
    "resultado": "aguardando_intervalo",
    "mensagem": "Aguardando intervalo de 2h entre posts. Faltam 3 min."
  },
  {
    "data": "2026-07-11T12:01:34.977Z",
    "resultado": "aguardando_intervalo",
    "mensagem": "Aguardando intervalo de 2h entre posts. Faltam 31 min."
  },
  {
    "data": "2026-07-11T11:58:10.352Z",
    "resultado": "story_glossario",
    "mensagem": "Story do glossário publicado: \"Come-cotas\"",
    "postId": "18143646832527436"
  },
  {
    "data": "2026-07-11T11:31:41.602Z",
    "resultado": "aguardando_intervalo",
    "mensagem": "Aguardando intervalo de 2h entre posts. Faltam 61 min."
  },
  {
    "data": "2026-07-11T11:15:04.989Z",
    "resultado": "aguardando_intervalo",
    "mensagem": "Aguardando intervalo de 2h entre posts. Faltam 78 min."
  },
  {
    "data": "2026-07-11T11:01:18.482Z",
    "resultado": "aguardando_intervalo",
    "mensagem": "Aguardando intervalo de 2h entre posts. Faltam 92 min."
  },
  {
    "data": "2026-07-11T10:32:19.717Z",
    "resultado": "postado",
    "mensagem": "Postagem realizada com sucesso (card): \"XP mantém otimismo com PIB e prevê dólar a R$ 5,00; veja os destaques da semana\".",
    "postId": "17899000296472240",
    "storyId": "17872702857623576",
    "reelId": null,
    "tipo": "card"
  },
  {
    "data": "2026-07-11T10:31:26.259Z",
    "resultado": "noticia_encontrada",
    "mensagem": "Notícia nova encontrada (peso 52): \"XP mantém otimismo com PIB e prevê dólar a R$ 5,00; veja os destaques da semana\". Realizando postagem..."
  },
  {
    "data": "2026-07-11T10:01:27.734Z",
    "resultado": "sem_noticia",
    "mensagem": "Nenhuma notícia nova na última hora. Nada foi postado."
  },
  {
    "data": "2026-07-11T09:59:44.775Z",
    "resultado": "sem_noticia",
    "mensagem": "Nenhuma notícia nova na última hora. Nada foi postado."
  },
  {
    "data": "2026-07-11T09:31:37.450Z",
    "resultado": "sem_noticia",
    "mensagem": "Nenhuma notícia nova na última hora. Nada foi postado."
  },
  {
    "data": "2026-07-11T09:01:23.961Z",
    "resultado": "sem_noticia",
    "mensagem": "Nenhuma notícia nova na última hora. Nada foi postado."
  },
  {
    "data": "2026-07-11T08:31:21.914Z",
    "resultado": "fora_horario",
    "mensagem": "Verificação fora do horário de pico (05:31 BRT). Postagens ocorrem entre 06h e 22h."
  },
  {
    "data": "2026-07-11T08:01:58.829Z",
    "resultado": "fora_horario",
    "mensagem": "Verificação fora do horário de pico (05:01 BRT). Postagens ocorrem entre 06h e 22h."
  },
  {
    "data": "2026-07-11T08:01:08.367Z",
    "resultado": "fora_horario",
    "mensagem": "Verificação fora do horário de pico (05:01 BRT). Postagens ocorrem entre 06h e 22h."
  },
  {
    "data": "2026-07-11T07:31:21.360Z",
    "resultado": "fora_horario",
    "mensagem": "Verificação fora do horário de pico (04:31 BRT). Postagens ocorrem entre 06h e 22h."
  },
  {
    "data": "2026-07-11T07:01:17.327Z",
    "resultado": "fora_horario",
    "mensagem": "Verificação fora do horário de pico (04:01 BRT). Postagens ocorrem entre 06h e 22h."
  },
  {
    "data": "2026-07-11T06:31:12.449Z",
    "resultado": "fora_horario",
    "mensagem": "Verificação fora do horário de pico (03:31 BRT). Postagens ocorrem entre 06h e 22h."
  },
  {
    "data": "2026-07-11T06:01:20.034Z",
    "resultado": "fora_horario",
    "mensagem": "Verificação fora do horário de pico (03:01 BRT). Postagens ocorrem entre 06h e 22h."
  },
  {
    "data": "2026-07-11T05:43:52.169Z",
    "resultado": "fora_horario",
    "mensagem": "Verificação fora do horário de pico (02:43 BRT). Postagens ocorrem entre 06h e 22h."
  },
  {
    "data": "2026-07-11T05:31:18.955Z",
    "resultado": "fora_horario",
    "mensagem": "Verificação fora do horário de pico (02:31 BRT). Postagens ocorrem entre 06h e 22h."
  },
  {
    "data": "2026-07-11T05:01:55.578Z",
    "resultado": "fora_horario",
    "mensagem": "Verificação fora do horário de pico (02:01 BRT). Postagens ocorrem entre 06h e 22h."
  },
  {
    "data": "2026-07-11T04:31:19.404Z",
    "resultado": "fora_horario",
    "mensagem": "Verificação fora do horário de pico (01:31 BRT). Postagens ocorrem entre 06h e 22h."
  },
  {
    "data": "2026-07-11T04:01:31.158Z",
    "resultado": "fora_horario",
    "mensagem": "Verificação fora do horário de pico (01:01 BRT). Postagens ocorrem entre 06h e 22h."
  },
  {
    "data": "2026-07-11T03:31:17.551Z",
    "resultado": "fora_horario",
    "mensagem": "Verificação fora do horário de pico (00:31 BRT). Postagens ocorrem entre 06h e 22h."
  },
  {
    "data": "2026-07-11T03:01:21.556Z",
    "resultado": "fora_horario",
    "mensagem": "Verificação fora do horário de pico (00:01 BRT). Postagens ocorrem entre 06h e 22h."
  },
  {
    "data": "2026-07-11T02:51:51.795Z",
    "resultado": "fora_horario",
    "mensagem": "Verificação fora do horário de pico (23:51 BRT). Postagens ocorrem entre 06h e 22h."
  },
  {
    "data": "2026-07-11T02:31:55.528Z",
    "resultado": "fora_horario",
    "mensagem": "Verificação fora do horário de pico (23:31 BRT). Postagens ocorrem entre 06h e 22h."
  },
  {
    "data": "2026-07-11T02:01:24.944Z",
    "resultado": "fora_horario",
    "mensagem": "Verificação fora do horário de pico (23:01 BRT). Postagens ocorrem entre 06h e 22h."
  },
  {
    "data": "2026-07-11T01:31:28.527Z",
    "resultado": "fora_horario",
    "mensagem": "Verificação fora do horário de pico (22:31 BRT). Postagens ocorrem entre 06h e 22h."
  },
  {
    "data": "2026-07-11T01:01:18.893Z",
    "resultado": "fora_horario",
    "mensagem": "Verificação fora do horário de pico (22:01 BRT). Postagens ocorrem entre 06h e 22h."
  },
  {
    "data": "2026-07-11T00:32:49.693Z",
    "resultado": "postado",
    "mensagem": "Postagem realizada com sucesso (carrossel): \"HSAF11 mantém dividendos em R$ 0,95 por cota pelo 18º mês\".",
    "postId": "17900019384327008",
    "storyId": "18083270390249517",
    "reelId": null,
    "tipo": "carrossel"
  },
  {
    "data": "2026-07-11T00:31:28.222Z",
    "resultado": "noticia_encontrada",
    "mensagem": "Notícia nova encontrada (peso 28): \"HSAF11 mantém dividendos em R$ 0,95 por cota pelo 18º mês\". Realizando postagem..."
  },
  {
    "data": "2026-07-11T00:01:16.642Z",
    "resultado": "aguardando_intervalo",
    "mensagem": "Aguardando intervalo de 2h entre posts. Faltam 8 min."
  },
  {
    "data": "2026-07-10T23:57:16.229Z",
    "resultado": "reel_postado",
    "mensagem": "Resumo em vídeo do dia publicado com 2 notícia(s).",
    "reelId": "18092948672377140",
    "videoUrl": "https://raw.githubusercontent.com/convexanews/convexanews.github.io/main/bdi-cards/resumo-1783727774142.mp4",
    "noticias": [
      "Chips de memória caem até 50% em três semanas, mas Dahlia mantém aposta na IA",
      "Ibovespa Hoje Ao Vivo: Confira o que movimenta Bolsa, Dólar e Juros nesta sexta"
    ]
  },
  {
    "data": "2026-07-10T23:32:10.295Z",
    "resultado": "aguardando_intervalo",
    "mensagem": "Aguardando intervalo de 2h entre posts. Faltam 37 min."
  },
  {
    "data": "2026-07-10T23:31:21.149Z",
    "resultado": "aguardando_intervalo",
    "mensagem": "Aguardando intervalo de 2h entre posts. Faltam 38 min."
  },
  {
    "data": "2026-07-10T23:01:20.533Z",
    "resultado": "aguardando_intervalo",
    "mensagem": "Aguardando intervalo de 2h entre posts. Faltam 68 min."
  },
  {
    "data": "2026-07-10T22:31:25.352Z",
    "resultado": "aguardando_intervalo",
    "mensagem": "Aguardando intervalo de 2h entre posts. Faltam 98 min."
  },
  {
    "data": "2026-07-10T22:08:54.322Z",
    "resultado": "postado",
    "mensagem": "Postagem realizada com sucesso (reel): \"Ibovespa dispara quase 3% com IPCA surpreendente e renova máxima em quase dois meses\".",
    "postId": "18188086795377783",
    "storyId": null,
    "reelId": "18188086795377783",
    "tipo": "reel"
  },
  {
    "data": "2026-07-10T22:07:06.248Z",
    "resultado": "noticia_encontrada",
    "mensagem": "Notícia nova encontrada (peso 68): \"Ibovespa dispara quase 3% com IPCA surpreendente e renova máxima em quase dois meses\". Realizando postagem..."
  },
  {
    "data": "2026-07-10T22:02:31.109Z",
    "resultado": "erro",
    "mensagem": "Erro na execução automática: Command failed: git push"
  },
  {
    "data": "2026-07-10T22:01:34.052Z",
    "resultado": "noticia_encontrada",
    "mensagem": "Notícia nova encontrada (peso 68): \"Ibovespa dispara quase 3% com IPCA surpreendente e renova máxima em quase dois meses\". Realizando postagem..."
  },
  {
    "data": "2026-07-10T21:49:02.201Z",
    "resultado": "carrossel_fechamento",
    "mensagem": "Carrossel de fechamento publicado. Ibovespa: 177.866 +4,23%",
    "postId": "18125357005740041",
    "ibov": {
      "valor": "177.866",
      "variacao": "+4,23%"
    },
    "topAltas": [
      "CSNA3 +7,92%",
      "MGLU3 +7,41%",
      "BPAC11 +5,48%",
      "CSAN3 +5,44%",
      "HAPV3 +5,26%"
    ]
  },
  {
    "data": "2026-07-10T21:31:38.270Z",
    "resultado": "aguardando_intervalo",
    "mensagem": "Aguardando intervalo de 2h entre posts. Faltam 2 min."
  },
  {
    "data": "2026-07-10T21:01:30.009Z",
    "resultado": "aguardando_intervalo",
    "mensagem": "Aguardando intervalo de 2h entre posts. Faltam 33 min."
  },
  {
    "data": "2026-07-10T20:51:02.108Z",
    "resultado": "aguardando_intervalo",
    "mensagem": "Aguardando intervalo de 2h entre posts. Faltam 43 min."
  },
  {
    "data": "2026-07-10T20:31:21.707Z",
    "resultado": "aguardando_intervalo",
    "mensagem": "Aguardando intervalo de 2h entre posts. Faltam 63 min."
  },
  {
    "data": "2026-07-10T20:01:21.591Z",
    "resultado": "aguardando_intervalo",
    "mensagem": "Aguardando intervalo de 2h entre posts. Faltam 93 min."
  },
  {
    "data": "2026-07-10T19:33:31.954Z",
    "resultado": "postado",
    "mensagem": "Postagem realizada com sucesso (reel): \"Inflação abaixo do esperado já permite sonhar com mais cortes na Selic? Veja as projeções dos bancos\".",
    "postId": "17993181555004446",
    "storyId": null,
    "reelId": "17993181555004446",
    "tipo": "reel"
  },
  {
    "data": "2026-07-10T19:31:29.413Z",
    "resultado": "noticia_encontrada",
    "mensagem": "Notícia nova encontrada (peso 68): \"Inflação abaixo do esperado já permite sonhar com mais cortes na Selic? Veja as projeções dos bancos\". Realizando postagem..."
  },
  {
    "data": "2026-07-10T19:03:09.023Z",
    "resultado": "aguardando_intervalo",
    "mensagem": "Aguardando intervalo de 2h entre posts. Faltam 18 min."
  },
  {
    "data": "2026-07-10T19:01:28.151Z",
    "resultado": "aguardando_intervalo",
    "mensagem": "Aguardando intervalo de 2h entre posts. Faltam 19 min."
  },
  {
    "data": "2026-07-10T18:31:30.409Z",
    "resultado": "aguardando_intervalo",
    "mensagem": "Aguardando intervalo de 2h entre posts. Faltam 49 min."
  },
  {
    "data": "2026-07-10T18:01:28.575Z",
    "resultado": "aguardando_intervalo",
    "mensagem": "Aguardando intervalo de 2h entre posts. Faltam 79 min."
  },
  {
    "data": "2026-07-10T17:31:31.260Z",
    "resultado": "aguardando_intervalo",
    "mensagem": "Aguardando intervalo de 2h entre posts. Faltam 109 min."
  },
  {
    "data": "2026-07-10T17:21:18.023Z",
    "resultado": "aguardando_intervalo",
    "mensagem": "Aguardando intervalo de 2h entre posts. Faltam 120 min."
  },
  {
    "data": "2026-07-10T17:20:25.713Z",
    "resultado": "postado",
    "mensagem": "Postagem realizada com sucesso (reel): \"Fed revela resiliência surpreendente do sistema financeiro americano em meio a crises\".",
    "postId": "18067287470480257",
    "storyId": null,
    "reelId": "18067287470480257",
    "tipo": "reel"
  },
  {
    "data": "2026-07-10T17:18:05.642Z",
    "resultado": "noticia_encontrada",
    "mensagem": "Notícia nova encontrada (peso 83): \"Fed revela resiliência surpreendente do sistema financeiro americano em meio a crises\". Realizando postagem..."
  },
  {
    "data": "2026-07-10T16:02:02.057Z",
    "resultado": "aguardando_intervalo",
    "mensagem": "Aguardando intervalo de 2h entre posts. Faltam 2 min."
  },
  {
    "data": "2026-07-10T15:31:10.614Z",
    "resultado": "aguardando_intervalo",
    "mensagem": "Aguardando intervalo de 2h entre posts. Faltam 32 min."
  },
  {
    "data": "2026-07-10T15:14:56.745Z",
    "resultado": "aguardando_intervalo",
    "mensagem": "Aguardando intervalo de 2h entre posts. Faltam 49 min."
  },
  {
    "data": "2026-07-10T15:02:31.352Z",
    "resultado": "reel_postado",
    "mensagem": "Resumo em vídeo do dia publicado com 3 notícia(s).",
    "reelId": "18431120803192442",
    "videoUrl": "https://raw.githubusercontent.com/convexanews/convexanews.github.io/main/bdi-cards/resumo-1783695688874.mp4",
    "noticias": [
      "Ibovespa hoje fecha alta, seguindo NY, com ações de bancos; dólar cai para R$ 5,12",
      "Chips de memória caem até 50% em três semanas, mas Dahlia mantém aposta na IA",
      "Ibovespa Hoje Ao Vivo: Confira o que movimenta Bolsa, Dólar e Juros nesta sexta"
    ]
  },
  {
    "data": "2026-07-10T15:01:15.391Z",
    "resultado": "aguardando_intervalo",
    "mensagem": "Aguardando intervalo de 2h entre posts. Faltam 62 min."
  },
  {
    "data": "2026-07-10T14:31:16.341Z",
    "resultado": "aguardando_intervalo",
    "mensagem": "Aguardando intervalo de 2h entre posts. Faltam 92 min."
  },
  {
    "data": "2026-07-10T14:03:02.353Z",
    "resultado": "postado",
    "mensagem": "Postagem realizada com sucesso (reel): \"IPCA fraco reforça aposta em corte da Selic em agosto, mas petróleo mantém alerta\".",
    "postId": "18107058979997358",
    "storyId": null,
    "reelId": "18107058979997358",
    "tipo": "reel"
  },
  {
    "data": "2026-07-10T14:01:20.468Z",
    "resultado": "noticia_encontrada",
    "mensagem": "Notícia nova encontrada (peso 66): \"IPCA fraco reforça aposta em corte da Selic em agosto, mas petróleo mantém alerta\". Realizando postagem..."
  },
  {
    "data": "2026-07-10T13:32:03.224Z",
    "resultado": "alerta_recorde",
    "mensagem": "Alerta de recorde publicado: Ibovespa (NOVA MÁXIMA).",
    "postId": "18084350498179940"
  },
  {
    "data": "2026-07-10T13:31:22.127Z",
    "resultado": "aguardando_intervalo",
    "mensagem": "Aguardando intervalo de 2h entre posts. Faltam 2 min."
  },
  {
    "data": "2026-07-10T13:16:59.501Z",
    "resultado": "story_glossario",
    "mensagem": "Story do glossário publicado: \"Taxa de Administração\"",
    "postId": "18088314557451161"
  },
  {
    "data": "2026-07-10T13:01:17.293Z",
    "resultado": "aguardando_intervalo",
    "mensagem": "Aguardando intervalo de 2h entre posts. Faltam 32 min."
  },
  {
    "data": "2026-07-10T12:31:19.415Z",
    "resultado": "aguardando_intervalo",
    "mensagem": "Aguardando intervalo de 2h entre posts. Faltam 62 min."
  },
  {
    "data": "2026-07-10T12:27:20.858Z",
    "resultado": "aguardando_intervalo",
    "mensagem": "Aguardando intervalo de 2h entre posts. Faltam 66 min."
  },
  {
    "data": "2026-07-10T12:01:25.288Z",
    "resultado": "aguardando_intervalo",
    "mensagem": "Aguardando intervalo de 2h entre posts. Faltam 92 min."
  },
  {
    "data": "2026-07-10T11:32:50.446Z",
    "resultado": "postado",
    "mensagem": "Postagem realizada com sucesso (carrossel): \"Ibovespa Hoje Ao Vivo: Confira o que movimenta Bolsa, Dólar e Juros nesta sexta\".",
    "postId": "18383621257165945",
    "storyId": "18479889394097753",
    "reelId": null,
    "tipo": "carrossel"
  },
  {
    "data": "2026-07-10T11:31:26.794Z",
    "resultado": "noticia_encontrada",
    "mensagem": "Notícia nova encontrada (peso 55): \"Ibovespa Hoje Ao Vivo: Confira o que movimenta Bolsa, Dólar e Juros nesta sexta\". Realizando postagem..."
  },
  {
    "data": "2026-07-10T11:01:41.705Z",
    "resultado": "aguardando_intervalo",
    "mensagem": "Aguardando intervalo de 2h entre posts. Faltam 2 min."
  },
  {
    "data": "2026-07-10T10:32:02.171Z",
    "resultado": "aguardando_intervalo",
    "mensagem": "Aguardando intervalo de 2h entre posts. Faltam 32 min."
  },
  {
    "data": "2026-07-10T10:01:37.659Z",
    "resultado": "aguardando_intervalo",
    "mensagem": "Aguardando intervalo de 2h entre posts. Faltam 62 min."
  },
  {
    "data": "2026-07-10T09:40:58.442Z",
    "resultado": "aguardando_intervalo",
    "mensagem": "Aguardando intervalo de 2h entre posts. Faltam 83 min."
  },
  {
    "data": "2026-07-10T09:31:38.960Z",
    "resultado": "aguardando_intervalo",
    "mensagem": "Aguardando intervalo de 2h entre posts. Faltam 92 min."
  },
  {
    "data": "2026-07-10T09:03:16.362Z",
    "resultado": "postado",
    "mensagem": "Postagem realizada com sucesso (reel): \"Tempo Real: Ibovespa fecha semana de olho na inflação brasileira\".",
    "postId": "17945679495039252",
    "storyId": null,
    "reelId": "17945679495039252",
    "tipo": "reel"
  },
  {
    "data": "2026-07-10T09:01:36.959Z",
    "resultado": "noticia_encontrada",
    "mensagem": "Notícia nova encontrada (peso 39): \"Tempo Real: Ibovespa fecha semana de olho na inflação brasileira\". Realizando postagem..."
  },
  {
    "data": "2026-07-10T08:31:20.094Z",
    "resultado": "fora_horario",
    "mensagem": "Verificação fora do horário de pico (05:31 BRT). Postagens ocorrem entre 06h e 22h."
  },
  {
    "data": "2026-07-10T08:01:26.415Z",
    "resultado": "fora_horario",
    "mensagem": "Verificação fora do horário de pico (05:01 BRT). Postagens ocorrem entre 06h e 22h."
  },
  {
    "data": "2026-07-10T07:31:12.227Z",
    "resultado": "fora_horario",
    "mensagem": "Verificação fora do horário de pico (04:31 BRT). Postagens ocorrem entre 06h e 22h."
  },
  {
    "data": "2026-07-10T07:01:21.363Z",
    "resultado": "fora_horario",
    "mensagem": "Verificação fora do horário de pico (04:01 BRT). Postagens ocorrem entre 06h e 22h."
  },
  {
    "data": "2026-07-10T06:31:12.863Z",
    "resultado": "fora_horario",
    "mensagem": "Verificação fora do horário de pico (03:31 BRT). Postagens ocorrem entre 06h e 22h."
  },
  {
    "data": "2026-07-10T06:01:23.610Z",
    "resultado": "fora_horario",
    "mensagem": "Verificação fora do horário de pico (03:01 BRT). Postagens ocorrem entre 06h e 22h."
  },
  {
    "data": "2026-07-10T05:38:44.189Z",
    "resultado": "fora_horario",
    "mensagem": "Verificação fora do horário de pico (02:38 BRT). Postagens ocorrem entre 06h e 22h."
  },
  {
    "data": "2026-07-10T05:31:31.562Z",
    "resultado": "fora_horario",
    "mensagem": "Verificação fora do horário de pico (02:31 BRT). Postagens ocorrem entre 06h e 22h."
  },
  {
    "data": "2026-07-10T05:01:22.258Z",
    "resultado": "fora_horario",
    "mensagem": "Verificação fora do horário de pico (02:01 BRT). Postagens ocorrem entre 06h e 22h."
  },
  {
    "data": "2026-07-10T04:31:27.458Z",
    "resultado": "fora_horario",
    "mensagem": "Verificação fora do horário de pico (01:31 BRT). Postagens ocorrem entre 06h e 22h."
  },
  {
    "data": "2026-07-10T04:01:16.469Z",
    "resultado": "fora_horario",
    "mensagem": "Verificação fora do horário de pico (01:01 BRT). Postagens ocorrem entre 06h e 22h."
  },
  {
    "data": "2026-07-10T03:31:24.037Z",
    "resultado": "fora_horario",
    "mensagem": "Verificação fora do horário de pico (00:31 BRT). Postagens ocorrem entre 06h e 22h."
  },
  {
    "data": "2026-07-10T03:02:04.117Z",
    "resultado": "fora_horario",
    "mensagem": "Verificação fora do horário de pico (00:02 BRT). Postagens ocorrem entre 06h e 22h."
  },
  {
    "data": "2026-07-10T02:31:21.071Z",
    "resultado": "fora_horario",
    "mensagem": "Verificação fora do horário de pico (23:31 BRT). Postagens ocorrem entre 06h e 22h."
  },
  {
    "data": "2026-07-10T02:01:23.808Z",
    "resultado": "fora_horario",
    "mensagem": "Verificação fora do horário de pico (23:01 BRT). Postagens ocorrem entre 06h e 22h."
  },
  {
    "data": "2026-07-10T01:31:10.357Z",
    "resultado": "fora_horario",
    "mensagem": "Verificação fora do horário de pico (22:31 BRT). Postagens ocorrem entre 06h e 22h."
  },
  {
    "data": "2026-07-10T01:10:49.641Z",
    "resultado": "fora_horario",
    "mensagem": "Verificação fora do horário de pico (22:10 BRT). Postagens ocorrem entre 06h e 22h."
  },
  {
    "data": "2026-07-10T01:01:28.519Z",
    "resultado": "fora_horario",
    "mensagem": "Verificação fora do horário de pico (22:01 BRT). Postagens ocorrem entre 06h e 22h."
  },
  {
    "data": "2026-07-10T00:31:23.331Z",
    "resultado": "aguardando_intervalo",
    "mensagem": "Aguardando intervalo de 2h entre posts. Faltam 91 min."
  },
  {
    "data": "2026-07-10T00:04:49.830Z",
    "resultado": "reel_postado",
    "mensagem": "Resumo em vídeo do dia publicado com 4 notícia(s).",
    "reelId": "18109153564784929",
    "videoUrl": "https://raw.githubusercontent.com/convexanews/convexanews.github.io/main/bdi-cards/resumo-1783641760222.mp4",
    "noticias": [
      "Diretor financeiro da Omada Health vende US$ 85.423 em ações da empresa",
      "Dow Jones Futuro avança mesmo com tensão entre EUA e Irã",
      "Wall Street avança com recuperação do setor de tecnologia, apesar do conflito no Oriente Médio",
      "Ibovespa hoje fecha alta, seguindo NY, com ações de bancos; dólar cai para R$ 5,12"
    ]
  },
  {
    "data": "2026-07-09T23:31:30.790Z",
    "resultado": "aguardando_intervalo",
    "mensagem": "Aguardando intervalo de 2h entre posts. Faltam 2 min."
  },
  {
    "data": "2026-07-09T23:14:42.179Z",
    "resultado": "aguardando_intervalo",
    "mensagem": "Aguardando intervalo de 2h entre posts. Faltam 19 min."
  },
  {
    "data": "2026-07-09T23:01:18.436Z",
    "resultado": "aguardando_intervalo",
    "mensagem": "Aguardando intervalo de 2h entre posts. Faltam 32 min."
  },
  {
    "data": "2026-07-09T22:31:21.965Z",
    "resultado": "aguardando_intervalo",
    "mensagem": "Aguardando intervalo de 2h entre posts. Faltam 62 min."
  },
  {
    "data": "2026-07-09T22:11:52.325Z",
    "resultado": "carrossel_fechamento",
    "mensagem": "Carrossel de fechamento publicado. Ibovespa: 172.742 +0,42%",
    "postId": "17905544493448065",
    "ibov": {
      "valor": "172.742",
      "variacao": "+0,42%"
    },
    "topAltas": [
      "MGLU3 +7,76%",
      "RADL3 +4,68%",
      "BPAC11 +3,21%",
      "RDOR3 +3,14%",
      "CSAN3 +2,93%"
    ]
  },
  {
    "data": "2026-07-09T22:01:25.989Z",
    "resultado": "aguardando_intervalo",
    "mensagem": "Aguardando intervalo de 2h entre posts. Faltam 92 min."
  },
  {
    "data": "2026-07-09T21:37:51.934Z",
    "resultado": "aguardando_intervalo",
    "mensagem": "Aguardando intervalo de 2h entre posts. Faltam 116 min."
  },
  {
    "data": "2026-07-09T21:33:02.569Z",
    "resultado": "postado",
    "mensagem": "Postagem realizada com sucesso (carrossel): \"Ibovespa hoje fecha alta, seguindo NY, com ações de bancos; dólar cai para R$ 5,12\".",
    "postId": "18194877634374371",
    "storyId": "17920064922403340",
    "reelId": null,
    "tipo": "carrossel"
  },
  {
    "data": "2026-07-09T21:31:32.136Z",
    "resultado": "noticia_encontrada",
    "mensagem": "Notícia nova encontrada (peso 54): \"Ibovespa hoje fecha alta, seguindo NY, com ações de bancos; dólar cai para R$ 5,12\". Realizando postagem..."
  },
  {
    "data": "2026-07-09T21:01:27.241Z",
    "resultado": "aguardando_intervalo",
    "mensagem": "Aguardando intervalo de 2h entre posts. Faltam 2 min."
  },
  {
    "data": "2026-07-09T20:31:28.763Z",
    "resultado": "aguardando_intervalo",
    "mensagem": "Aguardando intervalo de 2h entre posts. Faltam 32 min."
  },
  {
    "data": "2026-07-09T20:01:27.473Z",
    "resultado": "aguardando_intervalo",
    "mensagem": "Aguardando intervalo de 2h entre posts. Faltam 62 min."
  },
  {
    "data": "2026-07-09T19:58:59.443Z",
    "resultado": "aguardando_intervalo",
    "mensagem": "Aguardando intervalo de 2h entre posts. Faltam 64 min."
  },
  {
    "data": "2026-07-09T19:31:20.586Z",
    "resultado": "aguardando_intervalo",
    "mensagem": "Aguardando intervalo de 2h entre posts. Faltam 92 min."
  },
  {
    "data": "2026-07-09T19:02:46.756Z",
    "resultado": "postado",
    "mensagem": "Postagem realizada com sucesso (reel): \"Opções de Copom da B3 apontam para corte de 0,25% na Selic em agosto\".",
    "postId": "18107976013803647",
    "storyId": null,
    "reelId": "18107976013803647",
    "tipo": "reel"
  },
  {
    "data": "2026-07-09T19:01:22.776Z",
    "resultado": "noticia_encontrada",
    "mensagem": "Notícia nova encontrada (peso 73): \"Opções de Copom da B3 apontam para corte de 0,25% na Selic em agosto\". Realizando postagem..."
  },
  {
    "data": "2026-07-09T18:31:39.265Z",
    "resultado": "aguardando_intervalo",
    "mensagem": "Aguardando intervalo de 2h entre posts. Faltam 2 min."
  },
  {
    "data": "2026-07-09T18:01:38.826Z",
    "resultado": "aguardando_intervalo",
    "mensagem": "Aguardando intervalo de 2h entre posts. Faltam 32 min."
  },
  {
    "data": "2026-07-09T17:58:58.977Z",
    "resultado": "aguardando_intervalo",
    "mensagem": "Aguardando intervalo de 2h entre posts. Faltam 35 min."
  },
  {
    "data": "2026-07-09T17:31:10.042Z",
    "resultado": "aguardando_intervalo",
    "mensagem": "Aguardando intervalo de 2h entre posts. Faltam 63 min."
  },
  {
    "data": "2026-07-09T17:01:19.277Z",
    "resultado": "aguardando_intervalo",
    "mensagem": "Aguardando intervalo de 2h entre posts. Faltam 92 min."
  },
  {
    "data": "2026-07-09T16:33:17.514Z",
    "resultado": "postado",
    "mensagem": "Postagem realizada com sucesso (reel): \"‘Trump não vai resolver conflito com o Irã’; acordo deve ficar para o próximo presidente, diz estrategista da Empiricus\".",
    "postId": "18136648042584830",
    "storyId": null,
    "reelId": "18136648042584830",
    "tipo": "reel"
  },
  {
    "data": "2026-07-09T16:31:32.397Z",
    "resultado": "noticia_encontrada",
    "mensagem": "Notícia nova encontrada (peso 61): \"‘Trump não vai resolver conflito com o Irã’; acordo deve ficar para o próximo presidente, diz estrategista da Empiricus\". Realizando postagem..."
  },
  {
    "data": "2026-07-09T16:01:22.958Z",
    "resultado": "aguardando_intervalo",
    "mensagem": "Aguardando intervalo de 2h entre posts. Faltam 2 min."
  },
  {
    "data": "2026-07-09T15:41:40.082Z",
    "resultado": "aguardando_intervalo",
    "mensagem": "Aguardando intervalo de 2h entre posts. Faltam 22 min."
  },
  {
    "data": "2026-07-09T15:31:35.682Z",
    "resultado": "aguardando_intervalo",
    "mensagem": "Aguardando intervalo de 2h entre posts. Faltam 32 min."
  },
  {
    "data": "2026-07-09T15:02:59.168Z",
    "resultado": "reel_postado",
    "mensagem": "Resumo em vídeo do dia publicado com 4 notícia(s).",
    "reelId": "18118670488896722",
    "videoUrl": "https://raw.githubusercontent.com/convexanews/convexanews.github.io/main/bdi-cards/resumo-1783609294574.mp4",
    "noticias": [
      "Tenda (TEND3): Ações caem 3% após prévia do 2T26; analistas respondem se é hora de comprar ou vender",
      "Diretor financeiro da Omada Health vende US$ 85.423 em ações da empresa",
      "Dow Jones Futuro avança mesmo com tensão entre EUA e Irã",
      "Wall Street avança com recuperação do setor de tecnologia, apesar do conflito no Oriente Médio"
    ]
  },
  {
    "data": "2026-07-09T15:01:22.135Z",
    "resultado": "aguardando_intervalo",
    "mensagem": "Aguardando intervalo de 2h entre posts. Faltam 62 min."
  },
  {
    "data": "2026-07-09T14:31:17.136Z",
    "resultado": "aguardando_intervalo",
    "mensagem": "Aguardando intervalo de 2h entre posts. Faltam 92 min."
  },
  {
    "data": "2026-07-09T14:02:45.078Z",
    "resultado": "postado",
    "mensagem": "Postagem realizada com sucesso (carrossel): \"Wall Street avança com recuperação do setor de tecnologia, apesar do conflito no Oriente Médio\".",
    "postId": "18006886292948088",
    "storyId": "17898928773528918",
    "reelId": null,
    "tipo": "carrossel"
  },
  {
    "data": "2026-07-09T14:01:21.957Z",
    "resultado": "noticia_encontrada",
    "mensagem": "Notícia nova encontrada (peso 55): \"Wall Street avança com recuperação do setor de tecnologia, apesar do conflito no Oriente Médio\". Realizando postagem..."
  },
  {
    "data": "2026-07-09T13:53:06.755Z",
    "resultado": "story_glossario",
    "mensagem": "Story do glossário publicado: \"Marcação a Mercado\"",
    "postId": "18125928763658745"
  },
  {
    "data": "2026-07-09T13:31:29.834Z",
    "resultado": "aguardando_intervalo",
    "mensagem": "Aguardando intervalo de 2h entre posts. Faltam 3 min."
  },
  {
    "data": "2026-07-09T13:11:26.540Z",
    "resultado": "aguardando_intervalo",
    "mensagem": "Aguardando intervalo de 2h entre posts. Faltam 23 min."
  },
  {
    "data": "2026-07-09T12:07:58.713Z",
    "resultado": "aguardando_intervalo",
    "mensagem": "Aguardando intervalo de 2h entre posts. Faltam 86 min."
  },
  {
    "data": "2026-07-09T12:03:37.971Z",
    "resultado": "aguardando_intervalo",
    "mensagem": "Aguardando intervalo de 2h entre posts. Faltam 91 min."
  },
  {
    "data": "2026-07-09T11:33:42.439Z",
    "resultado": "postado",
    "mensagem": "Postagem realizada com sucesso (reel): \"Bitcoin (BTC) volta a subir apesar dos temores da guerra no Irã; veja preços das criptomoedas nesta quinta-feira (9)\".",
    "postId": "18110068339910993",
    "storyId": null,
    "reelId": "18110068339910993",
    "tipo": "reel"
  },
  {
    "data": "2026-07-09T11:31:35.508Z",
    "resultado": "noticia_encontrada",
    "mensagem": "Notícia nova encontrada (peso 42): \"Bitcoin (BTC) volta a subir apesar dos temores da guerra no Irã; veja preços das criptomoedas nesta quinta-feira (9)\". Realizando postagem..."
  },
  {
    "data": "2026-07-09T11:06:31.049Z",
    "resultado": "aguardando_intervalo",
    "mensagem": "Aguardando intervalo de 2h entre posts. Faltam 2 min."
  },
  {
    "data": "2026-07-09T10:31:31.950Z",
    "resultado": "aguardando_intervalo",
    "mensagem": "Aguardando intervalo de 2h entre posts. Faltam 37 min."
  },
  {
    "data": "2026-07-09T10:01:37.662Z",
    "resultado": "aguardando_intervalo",
    "mensagem": "Aguardando intervalo de 2h entre posts. Faltam 67 min."
  },
  {
    "data": "2026-07-09T09:31:35.326Z",
    "resultado": "aguardando_intervalo",
    "mensagem": "Aguardando intervalo de 2h entre posts. Faltam 97 min."
  },
  {
    "data": "2026-07-09T09:08:28.046Z",
    "resultado": "postado",
    "mensagem": "Postagem realizada com sucesso (card): \"Dow Jones Futuro avança mesmo com tensão entre EUA e Irã\".",
    "postId": "18171008299384811",
    "storyId": "18081804167670913",
    "reelId": null,
    "tipo": "card"
  },
  {
    "data": "2026-07-09T09:07:23.074Z",
    "resultado": "noticia_encontrada",
    "mensagem": "Notícia nova encontrada (peso 42): \"Dow Jones Futuro avança mesmo com tensão entre EUA e Irã\". Realizando postagem..."
  },
  {
    "data": "2026-07-09T08:38:01.329Z",
    "resultado": "fora_horario",
    "mensagem": "Verificação fora do horário de pico (05:38 BRT). Postagens ocorrem entre 06h e 22h."
  },
  {
    "data": "2026-07-09T08:31:07.880Z",
    "resultado": "fora_horario",
    "mensagem": "Verificação fora do horário de pico (05:31 BRT). Postagens ocorrem entre 06h e 22h."
  },
  {
    "data": "2026-07-09T08:06:27.178Z",
    "resultado": "fora_horario",
    "mensagem": "Verificação fora do horário de pico (05:06 BRT). Postagens ocorrem entre 06h e 22h."
  },
  {
    "data": "2026-07-09T07:31:22.650Z",
    "resultado": "fora_horario",
    "mensagem": "Verificação fora do horário de pico (04:31 BRT). Postagens ocorrem entre 06h e 22h."
  },
  {
    "data": "2026-07-09T07:06:37.457Z",
    "resultado": "fora_horario",
    "mensagem": "Verificação fora do horário de pico (04:06 BRT). Postagens ocorrem entre 06h e 22h."
  },
  {
    "data": "2026-07-09T06:31:18.150Z",
    "resultado": "fora_horario",
    "mensagem": "Verificação fora do horário de pico (03:31 BRT). Postagens ocorrem entre 06h e 22h."
  },
  {
    "data": "2026-07-09T06:01:31.132Z",
    "resultado": "fora_horario",
    "mensagem": "Verificação fora do horário de pico (03:01 BRT). Postagens ocorrem entre 06h e 22h."
  },
  {
    "data": "2026-07-09T05:31:25.837Z",
    "resultado": "fora_horario",
    "mensagem": "Verificação fora do horário de pico (02:31 BRT). Postagens ocorrem entre 06h e 22h."
  },
  {
    "data": "2026-07-09T05:01:36.761Z",
    "resultado": "fora_horario",
    "mensagem": "Verificação fora do horário de pico (02:01 BRT). Postagens ocorrem entre 06h e 22h."
  },
  {
    "data": "2026-07-09T04:32:26.366Z",
    "resultado": "fora_horario",
    "mensagem": "Verificação fora do horário de pico (01:32 BRT). Postagens ocorrem entre 06h e 22h."
  },
  {
    "data": "2026-07-09T04:31:22.745Z",
    "resultado": "fora_horario",
    "mensagem": "Verificação fora do horário de pico (01:31 BRT). Postagens ocorrem entre 06h e 22h."
  },
  {
    "data": "2026-07-09T04:01:33.826Z",
    "resultado": "fora_horario",
    "mensagem": "Verificação fora do horário de pico (01:01 BRT). Postagens ocorrem entre 06h e 22h."
  },
  {
    "data": "2026-07-09T03:31:18.489Z",
    "resultado": "fora_horario",
    "mensagem": "Verificação fora do horário de pico (00:31 BRT). Postagens ocorrem entre 06h e 22h."
  },
  {
    "data": "2026-07-09T03:01:25.033Z",
    "resultado": "fora_horario",
    "mensagem": "Verificação fora do horário de pico (00:01 BRT). Postagens ocorrem entre 06h e 22h."
  },
  {
    "data": "2026-07-09T02:31:34.440Z",
    "resultado": "fora_horario",
    "mensagem": "Verificação fora do horário de pico (23:31 BRT). Postagens ocorrem entre 06h e 22h."
  },
  {
    "data": "2026-07-09T02:01:21.164Z",
    "resultado": "fora_horario",
    "mensagem": "Verificação fora do horário de pico (23:01 BRT). Postagens ocorrem entre 06h e 22h."
  },
  {
    "data": "2026-07-09T01:31:20.996Z",
    "resultado": "fora_horario",
    "mensagem": "Verificação fora do horário de pico (22:31 BRT). Postagens ocorrem entre 06h e 22h."
  },
  {
    "data": "2026-07-09T01:01:45.707Z",
    "resultado": "fora_horario",
    "mensagem": "Verificação fora do horário de pico (22:01 BRT). Postagens ocorrem entre 06h e 22h."
  },
  {
    "data": "2026-07-09T00:32:40.040Z",
    "resultado": "postado",
    "mensagem": "Postagem realizada com sucesso (carrossel): \"Diretor financeiro da Omada Health vende US$ 85.423 em ações da empresa\".",
    "postId": "17981053788013147",
    "storyId": null,
    "reelId": null,
    "tipo": "carrossel"
  },
  {
    "data": "2026-07-09T00:31:28.860Z",
    "resultado": "noticia_encontrada",
    "mensagem": "Notícia nova encontrada (peso 35): \"Diretor financeiro da Omada Health vende US$ 85.423 em ações da empresa\". Realizando postagem..."
  }
]