[
  {
    "data": "2026-07-17T10:49:50.148Z",
    "resultado": "aguardando_intervalo",
    "mensagem": "Aguardando intervalo de 2h entre posts. Faltam 14 min."
  },
  {
    "data": "2026-07-17T10:31:08.195Z",
    "resultado": "aguardando_intervalo",
    "mensagem": "Aguardando intervalo de 2h entre posts. Faltam 32 min."
  },
  {
    "data": "2026-07-17T10:01:33.490Z",
    "resultado": "aguardando_intervalo",
    "mensagem": "Aguardando intervalo de 2h entre posts. Faltam 62 min."
  },
  {
    "data": "2026-07-17T09:31:02.458Z",
    "resultado": "aguardando_intervalo",
    "mensagem": "Aguardando intervalo de 2h entre posts. Faltam 92 min."
  },
  {
    "data": "2026-07-17T09:02:54.060Z",
    "resultado": "postado",
    "mensagem": "Postagem realizada com sucesso (reel): \"Prévia do PIB no Brasil, indústria e confiança consumidor nos EUA e mais destaques\".",
    "postId": "17980539123047334",
    "storyId": null,
    "reelId": "17980539123047334",
    "tipo": "reel"
  },
  {
    "data": "2026-07-17T09:01:19.249Z",
    "resultado": "noticia_encontrada",
    "mensagem": "Notícia nova encontrada (peso 90): \"Prévia do PIB no Brasil, indústria e confiança consumidor nos EUA e mais destaques\". Realizando postagem..."
  },
  {
    "data": "2026-07-17T08:36:07.056Z",
    "resultado": "fora_horario",
    "mensagem": "Verificação fora do horário de pico (05:36 BRT). Postagens ocorrem entre 06h e 22h."
  },
  {
    "data": "2026-07-17T08:31:55.751Z",
    "resultado": "fora_horario",
    "mensagem": "Verificação fora do horário de pico (05:31 BRT). Postagens ocorrem entre 06h e 22h."
  },
  {
    "data": "2026-07-17T08:01:15.830Z",
    "resultado": "fora_horario",
    "mensagem": "Verificação fora do horário de pico (05:01 BRT). Postagens ocorrem entre 06h e 22h."
  },
  {
    "data": "2026-07-17T07:31:22.183Z",
    "resultado": "fora_horario",
    "mensagem": "Verificação fora do horário de pico (04:31 BRT). Postagens ocorrem entre 06h e 22h."
  },
  {
    "data": "2026-07-17T07:01:27.785Z",
    "resultado": "fora_horario",
    "mensagem": "Verificação fora do horário de pico (04:01 BRT). Postagens ocorrem entre 06h e 22h."
  },
  {
    "data": "2026-07-17T06:31:10.644Z",
    "resultado": "fora_horario",
    "mensagem": "Verificação fora do horário de pico (03:31 BRT). Postagens ocorrem entre 06h e 22h."
  },
  {
    "data": "2026-07-17T06:19:58.675Z",
    "resultado": "fora_horario",
    "mensagem": "Verificação fora do horário de pico (03:19 BRT). Postagens ocorrem entre 06h e 22h."
  },
  {
    "data": "2026-07-17T06:01:21.024Z",
    "resultado": "fora_horario",
    "mensagem": "Verificação fora do horário de pico (03:01 BRT). Postagens ocorrem entre 06h e 22h."
  },
  {
    "data": "2026-07-17T05:31:33.217Z",
    "resultado": "fora_horario",
    "mensagem": "Verificação fora do horário de pico (02:31 BRT). Postagens ocorrem entre 06h e 22h."
  },
  {
    "data": "2026-07-17T05:01:13.733Z",
    "resultado": "fora_horario",
    "mensagem": "Verificação fora do horário de pico (02:01 BRT). Postagens ocorrem entre 06h e 22h."
  },
  {
    "data": "2026-07-17T04:31:51.156Z",
    "resultado": "fora_horario",
    "mensagem": "Verificação fora do horário de pico (01:31 BRT). Postagens ocorrem entre 06h e 22h."
  },
  {
    "data": "2026-07-17T04:01:01.646Z",
    "resultado": "fora_horario",
    "mensagem": "Verificação fora do horário de pico (01:01 BRT). Postagens ocorrem entre 06h e 22h."
  },
  {
    "data": "2026-07-17T03:48:10.512Z",
    "resultado": "fora_horario",
    "mensagem": "Verificação fora do horário de pico (00:48 BRT). Postagens ocorrem entre 06h e 22h."
  },
  {
    "data": "2026-07-17T03:31:29.540Z",
    "resultado": "fora_horario",
    "mensagem": "Verificação fora do horário de pico (00:31 BRT). Postagens ocorrem entre 06h e 22h."
  },
  {
    "data": "2026-07-17T03:01:58.760Z",
    "resultado": "fora_horario",
    "mensagem": "Verificação fora do horário de pico (00:01 BRT). Postagens ocorrem entre 06h e 22h."
  },
  {
    "data": "2026-07-17T02:31:15.009Z",
    "resultado": "fora_horario",
    "mensagem": "Verificação fora do horário de pico (23:31 BRT). Postagens ocorrem entre 06h e 22h."
  },
  {
    "data": "2026-07-17T02:01:20.465Z",
    "resultado": "fora_horario",
    "mensagem": "Verificação fora do horário de pico (23:01 BRT). Postagens ocorrem entre 06h e 22h."
  },
  {
    "data": "2026-07-17T01:31:38.329Z",
    "resultado": "fora_horario",
    "mensagem": "Verificação fora do horário de pico (22:31 BRT). Postagens ocorrem entre 06h e 22h."
  },
  {
    "data": "2026-07-17T01:01:48.999Z",
    "resultado": "fora_horario",
    "mensagem": "Verificação fora do horário de pico (22:01 BRT). Postagens ocorrem entre 06h e 22h."
  },
  {
    "data": "2026-07-17T00:31:13.550Z",
    "resultado": "aguardando_intervalo",
    "mensagem": "Aguardando intervalo de 2h entre posts. Faltam 62 min."
  },
  {
    "data": "2026-07-17T00:07:51.279Z",
    "resultado": "aguardando_intervalo",
    "mensagem": "Aguardando intervalo de 2h entre posts. Faltam 85 min."
  },
  {
    "data": "2026-07-17T00:01:08.017Z",
    "resultado": "aguardando_intervalo",
    "mensagem": "Aguardando intervalo de 2h entre posts. Faltam 92 min."
  },
  {
    "data": "2026-07-16T23:58:52.343Z",
    "resultado": "reel_postado",
    "mensagem": "Resumo em vídeo do dia publicado com 5 notícia(s).",
    "reelId": "18448061101142452",
    "videoUrl": "https://raw.githubusercontent.com/convexanews/convexanews.github.io/main/bdi-cards/resumo-1784246209784.mp4",
    "noticias": [
      "Ações da SIG despencam 22% após alerta de lucros e vendas fracas",
      "Chips pesam e Wall Street opera majoritariamente em queda; Oriente Médio continua no radar",
      "S&P 500 e Nasdaq caem com perdas em chips e foco em balanços e dados econômicos",
      "Netflix desaponta em receita no 2T26 e reduz guidance para o ano; ação tomba 8% em NY",
      "Retaliação do Brasil aos EUA pode envolver royalties do audiovisual e patentes farmacêuticas, dizem fontes"
    ]
  },
  {
    "data": "2026-07-16T23:32:31.521Z",
    "resultado": "postado",
    "mensagem": "Postagem realizada com sucesso (card): \"Retaliação do Brasil aos EUA pode envolver royalties do audiovisual e patentes farmacêuticas, dizem fontes\".",
    "postId": "18028965608837313",
    "storyId": null,
    "reelId": null,
    "tipo": "card"
  },
  {
    "data": "2026-07-16T23:31:36.036Z",
    "resultado": "noticia_encontrada",
    "mensagem": "Notícia nova encontrada (peso 35): \"Retaliação do Brasil aos EUA pode envolver royalties do audiovisual e patentes farmacêuticas, dizem fontes\". Realizando postagem..."
  },
  {
    "data": "2026-07-16T23:01:08.419Z",
    "resultado": "aguardando_intervalo",
    "mensagem": "Aguardando intervalo de 2h entre posts. Faltam 2 min."
  },
  {
    "data": "2026-07-16T22:59:49.601Z",
    "resultado": "aguardando_intervalo",
    "mensagem": "Aguardando intervalo de 2h entre posts. Faltam 4 min."
  },
  {
    "data": "2026-07-16T22:31:45.327Z",
    "resultado": "aguardando_intervalo",
    "mensagem": "Aguardando intervalo de 2h entre posts. Faltam 32 min."
  },
  {
    "data": "2026-07-16T22:01:16.247Z",
    "resultado": "aguardando_intervalo",
    "mensagem": "Aguardando intervalo de 2h entre posts. Faltam 62 min."
  },
  {
    "data": "2026-07-16T21:53:37.655Z",
    "resultado": "carrossel_fechamento",
    "mensagem": "Carrossel de fechamento publicado. Ibovespa: 173.825 -1,59%",
    "postId": "17946715773229249",
    "ibov": {
      "valor": "173.825",
      "variacao": "-1,59%"
    },
    "topAltas": [
      "BBAS3 +1,02%",
      "SUZB3 +0,53%",
      "ABEV3 +0,19%",
      "RAIZ4 +0,00%",
      "TOTS3 -0,07%"
    ]
  },
  {
    "data": "2026-07-16T21:34:01.084Z",
    "resultado": "aguardando_intervalo",
    "mensagem": "Aguardando intervalo de 2h entre posts. Faltam 90 min."
  },
  {
    "data": "2026-07-16T21:31:19.472Z",
    "resultado": "aguardando_intervalo",
    "mensagem": "Aguardando intervalo de 2h entre posts. Faltam 92 min."
  },
  {
    "data": "2026-07-16T21:03:02.039Z",
    "resultado": "postado",
    "mensagem": "Postagem realizada com sucesso (carrossel): \"Netflix desaponta em receita no 2T26 e reduz guidance para o ano; ação tomba 8% em NY\".",
    "postId": "18119148953308534",
    "storyId": "17978271399109411",
    "reelId": null,
    "tipo": "carrossel"
  },
  {
    "data": "2026-07-16T21:01:34.654Z",
    "resultado": "noticia_encontrada",
    "mensagem": "Notícia nova encontrada (peso 47): \"Netflix desaponta em receita no 2T26 e reduz guidance para o ano; ação tomba 8% em NY\". Realizando postagem..."
  },
  {
    "data": "2026-07-16T20:31:22.484Z",
    "resultado": "aguardando_intervalo",
    "mensagem": "Aguardando intervalo de 2h entre posts. Faltam 2 min."
  },
  {
    "data": "2026-07-16T20:04:43.639Z",
    "resultado": "aguardando_intervalo",
    "mensagem": "Aguardando intervalo de 2h entre posts. Faltam 29 min."
  },
  {
    "data": "2026-07-16T20:01:20.319Z",
    "resultado": "aguardando_intervalo",
    "mensagem": "Aguardando intervalo de 2h entre posts. Faltam 32 min."
  },
  {
    "data": "2026-07-16T19:31:17.227Z",
    "resultado": "aguardando_intervalo",
    "mensagem": "Aguardando intervalo de 2h entre posts. Faltam 62 min."
  },
  {
    "data": "2026-07-16T19:01:11.413Z",
    "resultado": "aguardando_intervalo",
    "mensagem": "Aguardando intervalo de 2h entre posts. Faltam 92 min."
  },
  {
    "data": "2026-07-16T18:42:09.413Z",
    "resultado": "aguardando_intervalo",
    "mensagem": "Aguardando intervalo de 2h entre posts. Faltam 111 min."
  },
  {
    "data": "2026-07-16T18:32:47.756Z",
    "resultado": "postado",
    "mensagem": "Postagem realizada com sucesso (reel): \"Novas tarifas dos Estados Unidos impactam principalmente as empresas de pequeno porte, diz sócio da Voga Investimentos\".",
    "postId": "18477497953102993",
    "storyId": null,
    "reelId": "18477497953102993",
    "tipo": "reel"
  },
  {
    "data": "2026-07-16T18:31:06.972Z",
    "resultado": "noticia_encontrada",
    "mensagem": "Notícia nova encontrada (peso 48): \"Novas tarifas dos Estados Unidos impactam principalmente as empresas de pequeno porte, diz sócio da Voga Investimentos\". Realizando postagem..."
  },
  {
    "data": "2026-07-16T18:01:06.624Z",
    "resultado": "aguardando_intervalo",
    "mensagem": "Aguardando intervalo de 2h entre posts. Faltam 2 min."
  },
  {
    "data": "2026-07-16T17:31:55.568Z",
    "resultado": "aguardando_intervalo",
    "mensagem": "Aguardando intervalo de 2h entre posts. Faltam 31 min."
  },
  {
    "data": "2026-07-16T17:20:46.907Z",
    "resultado": "aguardando_intervalo",
    "mensagem": "Aguardando intervalo de 2h entre posts. Faltam 42 min."
  },
  {
    "data": "2026-07-16T17:01:04.314Z",
    "resultado": "aguardando_intervalo",
    "mensagem": "Aguardando intervalo de 2h entre posts. Faltam 62 min."
  },
  {
    "data": "2026-07-16T16:31:23.667Z",
    "resultado": "aguardando_intervalo",
    "mensagem": "Aguardando intervalo de 2h entre posts. Faltam 92 min."
  },
  {
    "data": "2026-07-16T16:02:31.463Z",
    "resultado": "postado",
    "mensagem": "Postagem realizada com sucesso (card): \"S&P 500 e Nasdaq caem com perdas em chips e foco em balanços e dados econômicos\".",
    "postId": "18041887418619184",
    "storyId": "18108322670013687",
    "reelId": null,
    "tipo": "card"
  },
  {
    "data": "2026-07-16T16:01:34.413Z",
    "resultado": "noticia_encontrada",
    "mensagem": "Notícia nova encontrada (peso 49): \"S&P 500 e Nasdaq caem com perdas em chips e foco em balanços e dados econômicos\". Realizando postagem..."
  },
  {
    "data": "2026-07-16T15:44:39.731Z",
    "resultado": "aguardando_intervalo",
    "mensagem": "Aguardando intervalo de 2h entre posts. Faltam 17 min."
  },
  {
    "data": "2026-07-16T15:31:08.854Z",
    "resultado": "aguardando_intervalo",
    "mensagem": "Aguardando intervalo de 2h entre posts. Faltam 31 min."
  },
  {
    "data": "2026-07-16T15:03:11.656Z",
    "resultado": "reel_postado",
    "mensagem": "Resumo em vídeo do dia publicado com 3 notícia(s).",
    "reelId": "18012455354728320",
    "videoUrl": "https://raw.githubusercontent.com/convexanews/convexanews.github.io/main/bdi-cards/resumo-1784214108175.mp4",
    "noticias": [
      "Gerdau (GGBR4) e Usiminas (USIM5): Morgan Stanley eleva preços-alvo, mas mantém cautela",
      "Ações da SIG despencam 22% após alerta de lucros e vendas fracas",
      "Chips pesam e Wall Street opera majoritariamente em queda; Oriente Médio continua no radar"
    ]
  },
  {
    "data": "2026-07-16T15:01:34.254Z",
    "resultado": "aguardando_intervalo",
    "mensagem": "Aguardando intervalo de 2h entre posts. Faltam 60 min."
  },
  {
    "data": "2026-07-16T14:32:11.445Z",
    "resultado": "aguardando_intervalo",
    "mensagem": "Aguardando intervalo de 2h entre posts. Faltam 90 min."
  },
  {
    "data": "2026-07-16T14:02:58.830Z",
    "resultado": "aguardando_intervalo",
    "mensagem": "Aguardando intervalo de 2h entre posts. Faltam 119 min."
  },
  {
    "data": "2026-07-16T14:01:12.591Z",
    "resultado": "postado",
    "mensagem": "Postagem realizada com sucesso (carrossel): \"Chips pesam e Wall Street opera majoritariamente em queda; Oriente Médio continua no radar\".",
    "postId": "18114134417297234",
    "storyId": "17917939209205795",
    "reelId": null,
    "tipo": "carrossel"
  },
  {
    "data": "2026-07-16T13:59:42.336Z",
    "resultado": "noticia_encontrada",
    "mensagem": "Notícia nova encontrada (peso 58): \"Chips pesam e Wall Street opera majoritariamente em queda; Oriente Médio continua no radar\". Realizando postagem..."
  },
  {
    "data": "2026-07-16T13:31:28.955Z",
    "resultado": "aguardando_intervalo",
    "mensagem": "Aguardando intervalo de 2h entre posts. Faltam 3 min."
  },
  {
    "data": "2026-07-16T13:01:39.133Z",
    "resultado": "aguardando_intervalo",
    "mensagem": "Aguardando intervalo de 2h entre posts. Faltam 32 min."
  },
  {
    "data": "2026-07-16T12:31:31.986Z",
    "resultado": "aguardando_intervalo",
    "mensagem": "Aguardando intervalo de 2h entre posts. Faltam 62 min."
  },
  {
    "data": "2026-07-16T12:25:28.583Z",
    "resultado": "story_glossario",
    "mensagem": "Story do glossário publicado: \"Day Trade\"",
    "postId": "17959143021153175"
  },
  {
    "data": "2026-07-16T12:01:22.359Z",
    "resultado": "aguardando_intervalo",
    "mensagem": "Aguardando intervalo de 2h entre posts. Faltam 93 min."
  },
  {
    "data": "2026-07-16T11:43:14.642Z",
    "resultado": "aguardando_intervalo",
    "mensagem": "Aguardando intervalo de 2h entre posts. Faltam 111 min."
  },
  {
    "data": "2026-07-16T11:33:29.575Z",
    "resultado": "postado",
    "mensagem": "Postagem realizada com sucesso (reel): \"Fundo imobiliário anuncia recompra de até 10% das cotas; IFIX avança\".",
    "postId": "18386964250163947",
    "storyId": null,
    "reelId": "18386964250163947",
    "tipo": "reel"
  },
  {
    "data": "2026-07-16T11:31:39.366Z",
    "resultado": "noticia_encontrada",
    "mensagem": "Notícia nova encontrada (peso 44): \"Fundo imobiliário anuncia recompra de até 10% das cotas; IFIX avança\". Realizando postagem..."
  },
  {
    "data": "2026-07-16T11:01:20.546Z",
    "resultado": "aguardando_intervalo",
    "mensagem": "Aguardando intervalo de 2h entre posts. Faltam 1 min."
  },
  {
    "data": "2026-07-16T10:31:31.106Z",
    "resultado": "aguardando_intervalo",
    "mensagem": "Aguardando intervalo de 2h entre posts. Faltam 31 min."
  },
  {
    "data": "2026-07-16T10:01:39.615Z",
    "resultado": "aguardando_intervalo",
    "mensagem": "Aguardando intervalo de 2h entre posts. Faltam 61 min."
  },
  {
    "data": "2026-07-16T09:35:56.966Z",
    "resultado": "aguardando_intervalo",
    "mensagem": "Aguardando intervalo de 2h entre posts. Faltam 87 min."
  },
  {
    "data": "2026-07-16T09:31:24.260Z",
    "resultado": "aguardando_intervalo",
    "mensagem": "Aguardando intervalo de 2h entre posts. Faltam 91 min."
  },
  {
    "data": "2026-07-16T09:02:17.109Z",
    "resultado": "postado",
    "mensagem": "Postagem realizada com sucesso (card): \"Ações da SIG despencam 22% após alerta de lucros e vendas fracas\".",
    "postId": "18103814827882569",
    "storyId": "17999250128957230",
    "reelId": null,
    "tipo": "card"
  },
  {
    "data": "2026-07-16T09:01:30.962Z",
    "resultado": "noticia_encontrada",
    "mensagem": "Notícia nova encontrada (peso 51): \"Ações da SIG despencam 22% após alerta de lucros e vendas fracas\". Realizando postagem..."
  },
  {
    "data": "2026-07-16T08:31:19.465Z",
    "resultado": "fora_horario",
    "mensagem": "Verificação fora do horário de pico (05:31 BRT). Postagens ocorrem entre 06h e 22h."
  },
  {
    "data": "2026-07-16T08:01:39.384Z",
    "resultado": "fora_horario",
    "mensagem": "Verificação fora do horário de pico (05:01 BRT). Postagens ocorrem entre 06h e 22h."
  },
  {
    "data": "2026-07-16T07:31:26.930Z",
    "resultado": "fora_horario",
    "mensagem": "Verificação fora do horário de pico (04:31 BRT). Postagens ocorrem entre 06h e 22h."
  },
  {
    "data": "2026-07-16T07:24:59.713Z",
    "resultado": "fora_horario",
    "mensagem": "Verificação fora do horário de pico (04:24 BRT). Postagens ocorrem entre 06h e 22h."
  },
  {
    "data": "2026-07-16T07:01:44.230Z",
    "resultado": "fora_horario",
    "mensagem": "Verificação fora do horário de pico (04:01 BRT). Postagens ocorrem entre 06h e 22h."
  },
  {
    "data": "2026-07-16T06:31:27.075Z",
    "resultado": "fora_horario",
    "mensagem": "Verificação fora do horário de pico (03:31 BRT). Postagens ocorrem entre 06h e 22h."
  },
  {
    "data": "2026-07-16T06:01:36.986Z",
    "resultado": "fora_horario",
    "mensagem": "Verificação fora do horário de pico (03:01 BRT). Postagens ocorrem entre 06h e 22h."
  },
  {
    "data": "2026-07-16T05:31:17.557Z",
    "resultado": "fora_horario",
    "mensagem": "Verificação fora do horário de pico (02:31 BRT). Postagens ocorrem entre 06h e 22h."
  },
  {
    "data": "2026-07-16T05:01:39.828Z",
    "resultado": "fora_horario",
    "mensagem": "Verificação fora do horário de pico (02:01 BRT). Postagens ocorrem entre 06h e 22h."
  },
  {
    "data": "2026-07-16T04:40:19.476Z",
    "resultado": "fora_horario",
    "mensagem": "Verificação fora do horário de pico (01:40 BRT). Postagens ocorrem entre 06h e 22h."
  },
  {
    "data": "2026-07-16T04:31:25.686Z",
    "resultado": "fora_horario",
    "mensagem": "Verificação fora do horário de pico (01:31 BRT). Postagens ocorrem entre 06h e 22h."
  },
  {
    "data": "2026-07-16T04:01:48.956Z",
    "resultado": "fora_horario",
    "mensagem": "Verificação fora do horário de pico (01:01 BRT). Postagens ocorrem entre 06h e 22h."
  },
  {
    "data": "2026-07-16T03:31:16.812Z",
    "resultado": "fora_horario",
    "mensagem": "Verificação fora do horário de pico (00:31 BRT). Postagens ocorrem entre 06h e 22h."
  },
  {
    "data": "2026-07-16T03:01:23.399Z",
    "resultado": "fora_horario",
    "mensagem": "Verificação fora do horário de pico (00:01 BRT). Postagens ocorrem entre 06h e 22h."
  },
  {
    "data": "2026-07-16T02:31:34.106Z",
    "resultado": "fora_horario",
    "mensagem": "Verificação fora do horário de pico (23:31 BRT). Postagens ocorrem entre 06h e 22h."
  },
  {
    "data": "2026-07-16T02:01:21.372Z",
    "resultado": "fora_horario",
    "mensagem": "Verificação fora do horário de pico (23:01 BRT). Postagens ocorrem entre 06h e 22h."
  },
  {
    "data": "2026-07-16T01:31:26.010Z",
    "resultado": "fora_horario",
    "mensagem": "Verificação fora do horário de pico (22:31 BRT). Postagens ocorrem entre 06h e 22h."
  },
  {
    "data": "2026-07-16T01:02:55.024Z",
    "resultado": "fora_horario",
    "mensagem": "Verificação fora do horário de pico (22:02 BRT). Postagens ocorrem entre 06h e 22h."
  },
  {
    "data": "2026-07-16T01:01:30.050Z",
    "resultado": "fora_horario",
    "mensagem": "Verificação fora do horário de pico (22:01 BRT). Postagens ocorrem entre 06h e 22h."
  },
  {
    "data": "2026-07-16T00:31:24.995Z",
    "resultado": "aguardando_intervalo",
    "mensagem": "Aguardando intervalo de 2h entre posts. Faltam 32 min."
  },
  {
    "data": "2026-07-16T00:01:26.982Z",
    "resultado": "aguardando_intervalo",
    "mensagem": "Aguardando intervalo de 2h entre posts. Faltam 62 min."
  },
  {
    "data": "2026-07-15T23:59:09.110Z",
    "resultado": "reel_postado",
    "mensagem": "Resumo em vídeo do dia publicado com 3 notícia(s).",
    "reelId": "17888219700416961",
    "videoUrl": "https://raw.githubusercontent.com/convexanews/convexanews.github.io/main/bdi-cards/resumo-1784159838981.mp4",
    "noticias": [
      "Em reunião com Jamieson Greer, Brasil chama tarifa dos EUA de “injusta”; governo já prepara nova MP de apoio aos exportadores",
      "Ibovespa Hoje Ao Vivo: Confira o que movimenta Bolsa, Dólar e Juros nesta quarta",
      "Gerdau (GGBR4) e Usiminas (USIM5): Morgan Stanley eleva preços-alvo, mas mantém cautela"
    ]
  },
  {
    "data": "2026-07-15T23:31:24.262Z",
    "resultado": "aguardando_intervalo",
    "mensagem": "Aguardando intervalo de 2h entre posts. Faltam 92 min."
  },
  {
    "data": "2026-07-15T23:30:38.126Z",
    "resultado": "aguardando_intervalo",
    "mensagem": "Aguardando intervalo de 2h entre posts. Faltam 93 min."
  },
  {
    "data": "2026-07-15T23:02:52.117Z",
    "resultado": "postado",
    "mensagem": "Postagem realizada com sucesso (carrossel): \"Gerdau (GGBR4) e Usiminas (USIM5): Morgan Stanley eleva preços-alvo, mas mantém cautela\".",
    "postId": "18131851771613157",
    "storyId": "18231014737317019",
    "reelId": null,
    "tipo": "carrossel"
  },
  {
    "data": "2026-07-15T23:01:23.779Z",
    "resultado": "noticia_encontrada",
    "mensagem": "Notícia nova encontrada (peso 31): \"Gerdau (GGBR4) e Usiminas (USIM5): Morgan Stanley eleva preços-alvo, mas mantém cautela\". Realizando postagem..."
  },
  {
    "data": "2026-07-15T22:31:21.552Z",
    "resultado": "aguardando_intervalo",
    "mensagem": "Aguardando intervalo de 2h entre posts. Faltam 6 min."
  },
  {
    "data": "2026-07-15T22:04:10.055Z",
    "resultado": "aguardando_intervalo",
    "mensagem": "Aguardando intervalo de 2h entre posts. Faltam 33 min."
  },
  {
    "data": "2026-07-15T22:01:56.614Z",
    "resultado": "aguardando_intervalo",
    "mensagem": "Aguardando intervalo de 2h entre posts. Faltam 36 min."
  },
  {
    "data": "2026-07-15T21:45:42.982Z",
    "resultado": "carrossel_fechamento",
    "mensagem": "Carrossel de fechamento publicado. Ibovespa: 176.011 +0,15%",
    "postId": "18171463201442388",
    "ibov": {
      "valor": "176.011",
      "variacao": "+0,15%"
    },
    "topAltas": [
      "TOTS3 +4,18%",
      "GGBR4 +3,77%",
      "CSAN3 +1,03%",
      "SUZB3 +0,90%",
      "CSNA3 +0,77%"
    ]
  },
  {
    "data": "2026-07-15T21:31:41.658Z",
    "resultado": "aguardando_intervalo",
    "mensagem": "Aguardando intervalo de 2h entre posts. Faltam 66 min."
  },
  {
    "data": "2026-07-15T21:01:36.401Z",
    "resultado": "aguardando_intervalo",
    "mensagem": "Aguardando intervalo de 2h entre posts. Faltam 96 min."
  },
  {
    "data": "2026-07-15T20:37:02.389Z",
    "resultado": "postado",
    "mensagem": "Postagem realizada com sucesso (reel): \"Wall Street avança após mercado adiar aposta de alta nos juros pelo Fed; Oriente Médio fica no radar\".",
    "postId": "18108000559967946",
    "storyId": null,
    "reelId": "18108000559967946",
    "tipo": "reel"
  },
  {
    "data": "2026-07-15T20:35:19.890Z",
    "resultado": "noticia_encontrada",
    "mensagem": "Notícia nova encontrada (peso 88): \"Wall Street avança após mercado adiar aposta de alta nos juros pelo Fed; Oriente Médio fica no radar\". Realizando postagem..."
  },
  {
    "data": "2026-07-15T20:31:33.513Z",
    "resultado": "erro_alerta_recorde",
    "mensagem": "Erro ao verificar alerta de recorde: Unexpected token '<', \"<!doctype \"... is not valid JSON"
  },
  {
    "data": "2026-07-15T20:31:31.522Z",
    "resultado": "aguardando_intervalo",
    "mensagem": "Aguardando intervalo de 2h entre posts. Faltam 2 min."
  },
  {
    "data": "2026-07-15T20:01:21.368Z",
    "resultado": "aguardando_intervalo",
    "mensagem": "Aguardando intervalo de 2h entre posts. Faltam 32 min."
  },
  {
    "data": "2026-07-15T19:31:31.448Z",
    "resultado": "aguardando_intervalo",
    "mensagem": "Aguardando intervalo de 2h entre posts. Faltam 62 min."
  },
  {
    "data": "2026-07-15T19:16:29.995Z",
    "resultado": "aguardando_intervalo",
    "mensagem": "Aguardando intervalo de 2h entre posts. Faltam 77 min."
  },
  {
    "data": "2026-07-15T19:01:28.759Z",
    "resultado": "aguardando_intervalo",
    "mensagem": "Aguardando intervalo de 2h entre posts. Faltam 92 min."
  },
  {
    "data": "2026-07-15T18:33:03.168Z",
    "resultado": "postado",
    "mensagem": "Postagem realizada com sucesso (reel): \"Dois fatores que podem ajudar o Brasil a cortar juros, segundo HSBC\".",
    "postId": "18032613740818189",
    "storyId": null,
    "reelId": "18032613740818189",
    "tipo": "reel"
  },
  {
    "data": "2026-07-15T18:31:24.380Z",
    "resultado": "noticia_encontrada",
    "mensagem": "Notícia nova encontrada (peso 91): \"Dois fatores que podem ajudar o Brasil a cortar juros, segundo HSBC\". Realizando postagem..."
  },
  {
    "data": "2026-07-15T18:01:36.048Z",
    "resultado": "aguardando_intervalo",
    "mensagem": "Aguardando intervalo de 2h entre posts. Faltam 3 min."
  },
  {
    "data": "2026-07-15T17:48:22.935Z",
    "resultado": "aguardando_intervalo",
    "mensagem": "Aguardando intervalo de 2h entre posts. Faltam 16 min."
  },
  {
    "data": "2026-07-15T17:31:21.134Z",
    "resultado": "aguardando_intervalo",
    "mensagem": "Aguardando intervalo de 2h entre posts. Faltam 33 min."
  },
  {
    "data": "2026-07-15T17:02:36.514Z",
    "resultado": "aguardando_intervalo",
    "mensagem": "Aguardando intervalo de 2h entre posts. Faltam 62 min."
  },
  {
    "data": "2026-07-15T16:31:28.277Z",
    "resultado": "aguardando_intervalo",
    "mensagem": "Aguardando intervalo de 2h entre posts. Faltam 93 min."
  },
  {
    "data": "2026-07-15T16:25:12.361Z",
    "resultado": "aguardando_intervalo",
    "mensagem": "Aguardando intervalo de 2h entre posts. Faltam 100 min."
  },
  {
    "data": "2026-07-15T16:04:12.381Z",
    "resultado": "postado",
    "mensagem": "Postagem realizada com sucesso (reel): \"Gringos ingressam com R$ 1,5 bilhão na B3 em dia de inflação abaixo do esperado\".",
    "postId": "18123749074742594",
    "storyId": null,
    "reelId": "18123749074742594",
    "tipo": "reel"
  },
  {
    "data": "2026-07-15T16:01:45.000Z",
    "resultado": "noticia_encontrada",
    "mensagem": "Notícia nova encontrada (peso 77): \"Gringos ingressam com R$ 1,5 bilhão na B3 em dia de inflação abaixo do esperado\". Realizando postagem..."
  },
  {
    "data": "2026-07-15T15:31:16.646Z",
    "resultado": "aguardando_intervalo",
    "mensagem": "Aguardando intervalo de 2h entre posts. Faltam 2 min."
  },
  {
    "data": "2026-07-15T15:02:45.786Z",
    "resultado": "reel_postado",
    "mensagem": "Resumo em vídeo do dia publicado com 4 notícia(s).",
    "reelId": "17875749630623631",
    "videoUrl": "https://raw.githubusercontent.com/convexanews/convexanews.github.io/main/bdi-cards/resumo-1784127699621.mp4",
    "noticias": [
      "Inflação para baixo no Brasil e nos EUA pode trazer fluxo gringo de volta para B3?",
      "CACR11 volta a fechar no negativo; IFIX termina pregão estável",
      "Em reunião com Jamieson Greer, Brasil chama tarifa dos EUA de “injusta”; governo já prepara nova MP de apoio aos exportadores",
      "Ibovespa Hoje Ao Vivo: Confira o que movimenta Bolsa, Dólar e Juros nesta quarta"
    ]
  },
  {
    "data": "2026-07-15T15:01:27.563Z",
    "resultado": "aguardando_intervalo",
    "mensagem": "Aguardando intervalo de 2h entre posts. Faltam 32 min."
  },
  {
    "data": "2026-07-15T14:53:56.169Z",
    "resultado": "aguardando_intervalo",
    "mensagem": "Aguardando intervalo de 2h entre posts. Faltam 40 min."
  },
  {
    "data": "2026-07-15T14:31:28.393Z",
    "resultado": "aguardando_intervalo",
    "mensagem": "Aguardando intervalo de 2h entre posts. Faltam 62 min."
  },
  {
    "data": "2026-07-15T14:02:34.802Z",
    "resultado": "aguardando_intervalo",
    "mensagem": "Aguardando intervalo de 2h entre posts. Faltam 91 min."
  },
  {
    "data": "2026-07-15T13:33:07.876Z",
    "resultado": "postado",
    "mensagem": "Postagem realizada com sucesso (carrossel): \"Ibovespa Hoje Ao Vivo: Confira o que movimenta Bolsa, Dólar e Juros nesta quarta\".",
    "postId": "18098327918581584",
    "storyId": "18454011322141485",
    "reelId": null,
    "tipo": "carrossel"
  },
  {
    "data": "2026-07-15T13:31:47.375Z",
    "resultado": "noticia_encontrada",
    "mensagem": "Notícia nova encontrada (peso 55): \"Ibovespa Hoje Ao Vivo: Confira o que movimenta Bolsa, Dólar e Juros nesta quarta\". Realizando postagem..."
  },
  {
    "data": "2026-07-15T13:01:28.775Z",
    "resultado": "aguardando_intervalo",
    "mensagem": "Aguardando intervalo de 2h entre posts. Faltam 12 min."
  },
  {
    "data": "2026-07-15T12:52:52.270Z",
    "resultado": "aguardando_intervalo",
    "mensagem": "Aguardando intervalo de 2h entre posts. Faltam 20 min."
  },
  {
    "data": "2026-07-15T12:31:45.328Z",
    "resultado": "aguardando_intervalo",
    "mensagem": "Aguardando intervalo de 2h entre posts. Faltam 41 min."
  },
  {
    "data": "2026-07-15T12:20:49.809Z",
    "resultado": "story_glossario",
    "mensagem": "Story do glossário publicado: \"Stop Loss\"",
    "postId": "18135254524538053"
  },
  {
    "data": "2026-07-15T12:01:36.234Z",
    "resultado": "aguardando_intervalo",
    "mensagem": "Aguardando intervalo de 2h entre posts. Faltam 72 min."
  },
  {
    "data": "2026-07-15T11:31:32.670Z",
    "resultado": "aguardando_intervalo",
    "mensagem": "Aguardando intervalo de 2h entre posts. Faltam 102 min."
  },
  {
    "data": "2026-07-15T11:12:42.943Z",
    "resultado": "postado",
    "mensagem": "Postagem realizada com sucesso (reel): \"Mercados monitoram inflação mais fraca e tensão em Ormuz; Ibovespa em dólar cai hoje (15)\".",
    "postId": "18121101862801736",
    "storyId": null,
    "reelId": "18121101862801736",
    "tipo": "reel"
  },
  {
    "data": "2026-07-15T11:11:10.705Z",
    "resultado": "noticia_encontrada",
    "mensagem": "Notícia nova encontrada (peso 67): \"Mercados monitoram inflação mais fraca e tensão em Ormuz; Ibovespa em dólar cai hoje (15)\". Realizando postagem..."
  },
  {
    "data": "2026-07-15T11:02:04.525Z",
    "resultado": "aguardando_intervalo",
    "mensagem": "Aguardando intervalo de 2h entre posts. Faltam 1 min."
  },
  {
    "data": "2026-07-15T10:31:45.756Z",
    "resultado": "aguardando_intervalo",
    "mensagem": "Aguardando intervalo de 2h entre posts. Faltam 31 min."
  },
  {
    "data": "2026-07-15T10:01:26.529Z",
    "resultado": "aguardando_intervalo",
    "mensagem": "Aguardando intervalo de 2h entre posts. Faltam 62 min."
  },
  {
    "data": "2026-07-15T09:31:25.435Z",
    "resultado": "aguardando_intervalo",
    "mensagem": "Aguardando intervalo de 2h entre posts. Faltam 92 min."
  },
  {
    "data": "2026-07-15T09:11:12.237Z",
    "resultado": "aguardando_intervalo",
    "mensagem": "Aguardando intervalo de 2h entre posts. Faltam 112 min."
  },
  {
    "data": "2026-07-15T09:02:39.646Z",
    "resultado": "postado",
    "mensagem": "Postagem realizada com sucesso (card): \"Em reunião com Jamieson Greer, Brasil chama tarifa dos EUA de “injusta”; governo já prepara nova MP de apoio aos exportadores\".",
    "postId": "18111125464948052",
    "storyId": "17872149582547084",
    "reelId": null,
    "tipo": "card"
  },
  {
    "data": "2026-07-15T09:01:41.045Z",
    "resultado": "noticia_encontrada",
    "mensagem": "Notícia nova encontrada (peso 38): \"Em reunião com Jamieson Greer, Brasil chama tarifa dos EUA de “injusta”; governo já prepara nova MP de apoio aos exportadores\". Realizando postagem..."
  },
  {
    "data": "2026-07-15T08:31:29.176Z",
    "resultado": "fora_horario",
    "mensagem": "Verificação fora do horário de pico (05:31 BRT). Postagens ocorrem entre 06h e 22h."
  },
  {
    "data": "2026-07-15T08:02:02.046Z",
    "resultado": "fora_horario",
    "mensagem": "Verificação fora do horário de pico (05:02 BRT). Postagens ocorrem entre 06h e 22h."
  },
  {
    "data": "2026-07-15T07:31:36.168Z",
    "resultado": "fora_horario",
    "mensagem": "Verificação fora do horário de pico (04:31 BRT). Postagens ocorrem entre 06h e 22h."
  },
  {
    "data": "2026-07-15T07:01:21.262Z",
    "resultado": "fora_horario",
    "mensagem": "Verificação fora do horário de pico (04:01 BRT). Postagens ocorrem entre 06h e 22h."
  },
  {
    "data": "2026-07-15T06:38:09.452Z",
    "resultado": "alerta_recorde",
    "mensagem": "Alerta de recorde publicado: Bitcoin (NOVA MÁXIMA).",
    "postId": "18177417271411354"
  },
  {
    "data": "2026-07-15T06:37:28.048Z",
    "resultado": "fora_horario",
    "mensagem": "Verificação fora do horário de pico (03:37 BRT). Postagens ocorrem entre 06h e 22h."
  },
  {
    "data": "2026-07-15T06:32:15.954Z",
    "resultado": "fora_horario",
    "mensagem": "Verificação fora do horário de pico (03:32 BRT). Postagens ocorrem entre 06h e 22h."
  },
  {
    "data": "2026-07-15T06:01:20.536Z",
    "resultado": "fora_horario",
    "mensagem": "Verificação fora do horário de pico (03:01 BRT). Postagens ocorrem entre 06h e 22h."
  },
  {
    "data": "2026-07-15T05:31:18.596Z",
    "resultado": "fora_horario",
    "mensagem": "Verificação fora do horário de pico (02:31 BRT). Postagens ocorrem entre 06h e 22h."
  },
  {
    "data": "2026-07-15T05:01:21.344Z",
    "resultado": "fora_horario",
    "mensagem": "Verificação fora do horário de pico (02:01 BRT). Postagens ocorrem entre 06h e 22h."
  },
  {
    "data": "2026-07-15T04:31:24.352Z",
    "resultado": "fora_horario",
    "mensagem": "Verificação fora do horário de pico (01:31 BRT). Postagens ocorrem entre 06h e 22h."
  },
  {
    "data": "2026-07-15T04:07:28.940Z",
    "resultado": "fora_horario",
    "mensagem": "Verificação fora do horário de pico (01:07 BRT). Postagens ocorrem entre 06h e 22h."
  },
  {
    "data": "2026-07-15T04:01:24.392Z",
    "resultado": "fora_horario",
    "mensagem": "Verificação fora do horário de pico (01:01 BRT). Postagens ocorrem entre 06h e 22h."
  },
  {
    "data": "2026-07-15T03:31:13.563Z",
    "resultado": "fora_horario",
    "mensagem": "Verificação fora do horário de pico (00:31 BRT). Postagens ocorrem entre 06h e 22h."
  },
  {
    "data": "2026-07-15T03:01:19.092Z",
    "resultado": "fora_horario",
    "mensagem": "Verificação fora do horário de pico (00:01 BRT). Postagens ocorrem entre 06h e 22h."
  },
  {
    "data": "2026-07-15T02:31:30.865Z",
    "resultado": "fora_horario",
    "mensagem": "Verificação fora do horário de pico (23:31 BRT). Postagens ocorrem entre 06h e 22h."
  },
  {
    "data": "2026-07-15T02:01:23.532Z",
    "resultado": "fora_horario",
    "mensagem": "Verificação fora do horário de pico (23:01 BRT). Postagens ocorrem entre 06h e 22h."
  },
  {
    "data": "2026-07-15T01:31:18.308Z",
    "resultado": "fora_horario",
    "mensagem": "Verificação fora do horário de pico (22:31 BRT). Postagens ocorrem entre 06h e 22h."
  },
  {
    "data": "2026-07-15T01:01:34.105Z",
    "resultado": "fora_horario",
    "mensagem": "Verificação fora do horário de pico (22:01 BRT). Postagens ocorrem entre 06h e 22h."
  },
  {
    "data": "2026-07-15T00:51:39.157Z",
    "resultado": "aguardando_intervalo",
    "mensagem": "Aguardando intervalo de 2h entre posts. Faltam 12 min."
  },
  {
    "data": "2026-07-15T00:31:40.745Z",
    "resultado": "aguardando_intervalo",
    "mensagem": "Aguardando intervalo de 2h entre posts. Faltam 32 min."
  },
  {
    "data": "2026-07-15T00:01:27.959Z",
    "resultado": "aguardando_intervalo",
    "mensagem": "Aguardando intervalo de 2h entre posts. Faltam 62 min."
  },
  {
    "data": "2026-07-14T23:52:41.022Z",
    "resultado": "reel_postado",
    "mensagem": "Resumo em vídeo do dia publicado com 3 notícia(s).",
    "reelId": "18401971417081377",
    "videoUrl": "https://raw.githubusercontent.com/convexanews/convexanews.github.io/main/bdi-cards/resumo-1784073088607.mp4",
    "noticias": [
      "Ibovespa Hoje Ao Vivo: Bolsa sobe com CPI dos EUA e guerra em foco",
      "Inflação para baixo no Brasil e nos EUA pode trazer fluxo gringo de volta para B3?",
      "CACR11 volta a fechar no negativo; IFIX termina pregão estável"
    ]
  },
  {
    "data": "2026-07-14T23:31:25.720Z",
    "resultado": "aguardando_intervalo",
    "mensagem": "Aguardando intervalo de 2h entre posts. Faltam 92 min."
  },
  {
    "data": "2026-07-14T23:07:03.484Z",
    "resultado": "aguardando_intervalo",
    "mensagem": "Aguardando intervalo de 2h entre posts. Faltam 116 min."
  },
  {
    "data": "2026-07-14T23:03:00.636Z",
    "resultado": "postado",
    "mensagem": "Postagem realizada com sucesso (carrossel): \"CACR11 volta a fechar no negativo; IFIX termina pregão estável\".",
    "postId": "17921371770402104",
    "storyId": "17999270516995048",
    "reelId": null,
    "tipo": "carrossel"
  },
  {
    "data": "2026-07-14T23:01:21.812Z",
    "resultado": "noticia_encontrada",
    "mensagem": "Notícia nova encontrada (peso 25): \"CACR11 volta a fechar no negativo; IFIX termina pregão estável\". Realizando postagem..."
  },
  {
    "data": "2026-07-14T22:31:21.626Z",
    "resultado": "aguardando_intervalo",
    "mensagem": "Aguardando intervalo de 2h entre posts. Faltam 10 min."
  },
  {
    "data": "2026-07-14T22:01:54.072Z",
    "resultado": "aguardando_intervalo",
    "mensagem": "Aguardando intervalo de 2h entre posts. Faltam 39 min."
  },
  {
    "data": "2026-07-14T22:00:46.063Z",
    "resultado": "aguardando_intervalo",
    "mensagem": "Aguardando intervalo de 2h entre posts. Faltam 40 min."
  },
  {
    "data": "2026-07-14T21:44:49.071Z",
    "resultado": "carrossel_fechamento",
    "mensagem": "Carrossel de fechamento publicado. Ibovespa: 176.641 -0,69%",
    "postId": "18334783123253039",
    "ibov": {
      "valor": "176.641",
      "variacao": "-0,69%"
    },
    "topAltas": [
      "HAPV3 +6,98%",
      "RADL3 +2,20%",
      "GGBR4 +2,19%",
      "EQTL3 +1,84%",
      "BBAS3 +1,73%"
    ]
  },
  {
    "data": "2026-07-14T21:31:57.289Z",
    "resultado": "aguardando_intervalo",
    "mensagem": "Aguardando intervalo de 2h entre posts. Faltam 69 min."
  },
  {
    "data": "2026-07-14T21:01:35.172Z",
    "resultado": "aguardando_intervalo",
    "mensagem": "Aguardando intervalo de 2h entre posts. Faltam 100 min."
  },
  {
    "data": "2026-07-14T20:40:45.974Z",
    "resultado": "postado",
    "mensagem": "Postagem realizada com sucesso (reel): \"Wall Street tem alta após inflação abaixo do esperado reduzir apostas de elevação nos juros pelo Fed\".",
    "postId": "18060533594583475",
    "storyId": null,
    "reelId": "18060533594583475",
    "tipo": "reel"
  },
  {
    "data": "2026-07-14T20:39:03.487Z",
    "resultado": "noticia_encontrada",
    "mensagem": "Notícia nova encontrada (peso 95): \"Wall Street tem alta após inflação abaixo do esperado reduzir apostas de elevação nos juros pelo Fed\". Realizando postagem..."
  },
  {
    "data": "2026-07-14T20:31:23.747Z",
    "resultado": "aguardando_intervalo",
    "mensagem": "Aguardando intervalo de 2h entre posts. Faltam 2 min."
  },
  {
    "data": "2026-07-14T20:01:25.989Z",
    "resultado": "aguardando_intervalo",
    "mensagem": "Aguardando intervalo de 2h entre posts. Faltam 32 min."
  },
  {
    "data": "2026-07-14T19:31:31.460Z",
    "resultado": "aguardando_intervalo",
    "mensagem": "Aguardando intervalo de 2h entre posts. Faltam 62 min."
  },
  {
    "data": "2026-07-14T19:24:04.416Z",
    "resultado": "aguardando_intervalo",
    "mensagem": "Aguardando intervalo de 2h entre posts. Faltam 70 min."
  },
  {
    "data": "2026-07-14T19:01:26.095Z",
    "resultado": "aguardando_intervalo",
    "mensagem": "Aguardando intervalo de 2h entre posts. Faltam 92 min."
  },
  {
    "data": "2026-07-14T18:33:22.100Z",
    "resultado": "postado",
    "mensagem": "Postagem realizada com sucesso (reel): \"Ibovespa pode chegar aos 300 mil pontos, mas sob uma condição, diz ASA\".",
    "postId": "18159227458476033",
    "storyId": null,
    "reelId": "18159227458476033",
    "tipo": "reel"
  },
  {
    "data": "2026-07-14T18:31:33.598Z",
    "resultado": "noticia_encontrada",
    "mensagem": "Notícia nova encontrada (peso 74): \"Ibovespa pode chegar aos 300 mil pontos, mas sob uma condição, diz ASA\". Realizando postagem..."
  },
  {
    "data": "2026-07-14T18:02:10.839Z",
    "resultado": "aguardando_intervalo",
    "mensagem": "Aguardando intervalo de 2h entre posts. Faltam 1 min."
  },
  {
    "data": "2026-07-14T17:41:37.649Z",
    "resultado": "aguardando_intervalo",
    "mensagem": "Aguardando intervalo de 2h entre posts. Faltam 22 min."
  },
  {
    "data": "2026-07-14T17:31:18.792Z",
    "resultado": "aguardando_intervalo",
    "mensagem": "Aguardando intervalo de 2h entre posts. Faltam 32 min."
  },
  {
    "data": "2026-07-14T17:02:15.345Z",
    "resultado": "aguardando_intervalo",
    "mensagem": "Aguardando intervalo de 2h entre posts. Faltam 61 min."
  },
  {
    "data": "2026-07-14T16:31:32.375Z",
    "resultado": "aguardando_intervalo",
    "mensagem": "Aguardando intervalo de 2h entre posts. Faltam 92 min."
  },
  {
    "data": "2026-07-14T16:18:27.167Z",
    "resultado": "aguardando_intervalo",
    "mensagem": "Aguardando intervalo de 2h entre posts. Faltam 105 min."
  },
  {
    "data": "2026-07-14T16:03:05.152Z",
    "resultado": "postado",
    "mensagem": "Postagem realizada com sucesso (card): \"Inflação para baixo no Brasil e nos EUA pode trazer fluxo gringo de volta para B3?\".",
    "postId": "17926514571363468",
    "storyId": "18168881236446796",
    "reelId": null,
    "tipo": "card"
  }
]